jupyterlab_apimaker/__init__.py
jupyterlab_apimaker/_version.py
jupyterlab_apimaker/config.py
jupyterlab_apimaker/db.py
jupyterlab_apimaker/handlers.py
jupyterlab_apimaker/smce_vars.py
jupyterlab_apimaker/utils.py
jupyterlab_apimaker/flask_app_components/HealthResource.py
jupyterlab_apimaker/flask_app_components/TokenResource.py
jupyterlab_apimaker/flask_app_components/__init__.py
jupyterlab_apimaker/flask_app_components/custom_types.py
jupyterlab_apimaker/flask_app_components/db_utils.py
jupyterlab_apimaker/flask_app_components/decorators.py
jupyterlab_apimaker/flask_app_components/fix_requirements.py
jupyterlab_apimaker/flask_app_components/interceptors.py
jupyterlab_apimaker/iac/__init__.py
jupyterlab_apimaker/iac/main.py
jupyterlab_apimaker/iac/apprunner/__init__.py
jupyterlab_apimaker/iac/apprunner/app.py
jupyterlab_apimaker/iac/apprunner/apprunner_stack.py
jupyterlab_apimaker/iac/imports/__init__.py
jupyterlab_apimaker/iac/imports/k8s/__init__.py
jupyterlab_apimaker/iac/imports/k8s/py.typed
jupyterlab_apimaker/iac/imports/k8s/_jsii/__init__.py
jupyterlab_apimaker/iac/imports/k8s/_jsii/k8s@0.0.0.jsii.tgz
jupyterlab_apimaker/iac/k8s/__init__.py
jupyterlab_apimaker/iac/zappaiac/__init__.py
jupyterlab_apimaker/iac/zappaiac/app.py
jupyterlab_apimaker/labextension/build_log.json
jupyterlab_apimaker/labextension/package.json
jupyterlab_apimaker/labextension/static/lib_index_js.fe6662c1fde2e8a3df07.js
jupyterlab_apimaker/labextension/static/lib_index_js.fe6662c1fde2e8a3df07.js.map
jupyterlab_apimaker/labextension/static/node_modules_babel_runtime_helpers_esm_extends_js-node_modules_emotion_memoize_dist_emotion-m-00c0260.13a84c6fdca958831e84.js
jupyterlab_apimaker/labextension/static/node_modules_babel_runtime_helpers_esm_extends_js-node_modules_emotion_memoize_dist_emotion-m-00c0260.13a84c6fdca958831e84.js.map
jupyterlab_apimaker-0.1.257rc0.dist-info/LICENSE
jupyterlab_apimaker-0.1.257rc0.dist-info/METADATA
jupyterlab_apimaker-0.1.257rc0.dist-info/WHEEL
jupyterlab_apimaker-0.1.257rc0.dist-info/top_level.txt
jupyterlab_apimaker-0.1.257rc0.dist-info/RECORD
