Metadata-Version: 2.1
Name: jupyterlab-apimaker
Version: 0.1.257rc0
Summary: A JupyterLab extension to create APIs from Python functions.
Home-page: https://github.com/github_username/jupyterlab_apimaker
Author: Navteca LLC
Author-email: info@navteca.com
License: BSD-3-Clause
Keywords: Jupyter,JupyterLab,JupyterLab3
Platform: Linux
Platform: Mac OS X
Platform: Windows
Classifier: License :: OSI Approved :: BSD License
Classifier: Programming Language :: Python
Classifier: Programming Language :: Python :: 3
Classifier: Programming Language :: Python :: 3.6
Classifier: Programming Language :: Python :: 3.7
Classifier: Programming Language :: Python :: 3.8
Classifier: Programming Language :: Python :: 3.9
Classifier: Framework :: Jupyter
Classifier: Framework :: Jupyter :: JupyterLab
Classifier: Framework :: Jupyter :: JupyterLab :: 3
Classifier: Framework :: Jupyter :: JupyterLab :: Extensions
Classifier: Framework :: Jupyter :: JupyterLab :: Extensions :: Prebuilt
Requires-Python: >=3.6
License-File: LICENSE
Requires-Dist: jupyter-server <2,>=1.6
Requires-Dist: jupyterlab >=3.0.0
Requires-Dist: ipynbname
Requires-Dist: boto3
Requires-Dist: cdk8s ==1.1.15
Requires-Dist: aws-cdk.core >=1.134.0
Requires-Dist: aws-cdk.aws-apprunner >=1.134.0
